xmlsig/__init__.py
xmlsig/constants.py
xmlsig/ns.py
xmlsig/signature_context.py
xmlsig/template.py
xmlsig/utils.py
xmlsig/algorithms/__init__.py
xmlsig/algorithms/base.py
xmlsig/algorithms/hmac.py
xmlsig/algorithms/rsa.py
xmlsig/data/xmldsig-core-schema.xsd
xmlsig-1.0.1.dist-info/LICENSE
xmlsig-1.0.1.dist-info/METADATA
xmlsig-1.0.1.dist-info/WHEEL
xmlsig-1.0.1.dist-info/top_level.txt
xmlsig-1.0.1.dist-info/RECORD
